{
  "timestamp": "2026-03-23T18:00:00",
  "mean_score": 78.6,
  "best_score": 96,
  "decision": "scored",
  "cases": [
    {
      "case_id": "HN3-001",
      "quality_score": 88,
      "dimensions": {
        "structural_integrity": {
          "score": 15,
          "max": 15
        },
        "evidence_depth": {
          "score": 16,
          "max": 25
        },
        "tier_coverage": {
          "score": 10,
          "max": 10
        },
        "rating_calibration": {
          "score": 13,
          "max": 15
        },
        "source_quality": {
          "score": 15,
          "max": 15
        },
        "clinical_relevance": {
          "score": 9,
          "max": 10
        },
        "combo_supportive_coverage": {
          "score": 10,
          "max": 10
        }
      },
      "report_path": "experiment_reports\\HN3-001_report.json",
      "status": "evaluated"
    },
    {
      "case_id": "HN3-002",
      "quality_score": 86,
      "dimensions": {
        "structural_integrity": {
          "score": 15,
          "max": 15
        },
        "evidence_depth": {
          "score": 13,
          "max": 25
        },
        "tier_coverage": {
          "score": 10,
          "max": 10
        },
        "rating_calibration": {
          "score": 14,
          "max": 15
        },
        "source_quality": {
          "score": 15,
          "max": 15
        },
        "clinical_relevance": {
          "score": 9,
          "max": 10
        },
        "combo_supportive_coverage": {
          "score": 10,
          "max": 10
        }
      },
      "report_path": "experiment_reports\\HN3-002_report.json",
      "status": "evaluated"
    },
    {
      "case_id": "HN3-003",
      "quality_score": 84,
      "dimensions": {
        "structural_integrity": {
          "score": 15,
          "max": 15
        },
        "evidence_depth": {
          "score": 11,
          "max": 25
        },
        "tier_coverage": {
          "score": 10,
          "max": 10
        },
        "rating_calibration": {
          "score": 14,
          "max": 15
        },
        "source_quality": {
          "score": 15,
          "max": 15
        },
        "clinical_relevance": {
          "score": 9,
          "max": 10
        },
        "combo_supportive_coverage": {
          "score": 10,
          "max": 10
        }
      },
      "report_path": "experiment_reports\\HN3-003_report.json",
      "status": "evaluated"
    },
    {
      "case_id": "HN3-004",
      "quality_score": 86,
      "dimensions": {
        "structural_integrity": {
          "score": 15,
          "max": 15
        },
        "evidence_depth": {
          "score": 15,
          "max": 25
        },
        "tier_coverage": {
          "score": 8,
          "max": 10
        },
        "rating_calibration": {
          "score": 14,
          "max": 15
        },
        "source_quality": {
          "score": 15,
          "max": 15
        },
        "clinical_relevance": {
          "score": 9,
          "max": 10
        },
        "combo_supportive_coverage": {
          "score": 10,
          "max": 10
        }
      },
      "report_path": "experiment_reports\\HN3-004_report.json",
      "status": "evaluated"
    },
    {
      "case_id": "HN3-005",
      "quality_score": 86,
      "dimensions": {
        "structural_integrity": {
          "score": 15,
          "max": 15
        },
        "evidence_depth": {
          "score": 14,
          "max": 25
        },
        "tier_coverage": {
          "score": 10,
          "max": 10
        },
        "rating_calibration": {
          "score": 13,
          "max": 15
        },
        "source_quality": {
          "score": 15,
          "max": 15
        },
        "clinical_relevance": {
          "score": 9,
          "max": 10
        },
        "combo_supportive_coverage": {
          "score": 10,
          "max": 10
        }
      },
      "report_path": "experiment_reports\\HN3-005_report.json",
      "status": "evaluated"
    },
    {
      "case_id": "HN3-006",
      "quality_score": 75,
      "dimensions": {
        "structural_integrity": {
          "score": 15,
          "max": 15
        },
        "evidence_depth": {
          "score": 16,
          "max": 25
        },
        "tier_coverage": {
          "score": 10,
          "max": 10
        },
        "rating_calibration": {
          "score": 0,
          "max": 15
        },
        "source_quality": {
          "score": 15,
          "max": 15
        },
        "clinical_relevance": {
          "score": 9,
          "max": 10
        },
        "combo_supportive_coverage": {
          "score": 10,
          "max": 10
        }
      },
      "report_path": "experiment_reports\\HN3-006_report.json",
      "status": "evaluated"
    },
    {
      "case_id": "HN3-007",
      "quality_score": 70,
      "dimensions": {
        "structural_integrity": {
          "score": 15,
          "max": 15
        },
        "evidence_depth": {
          "score": 12,
          "max": 25
        },
        "tier_coverage": {
          "score": 10,
          "max": 10
        },
        "rating_calibration": {
          "score": 0,
          "max": 15
        },
        "source_quality": {
          "score": 14,
          "max": 15
        },
        "clinical_relevance": {
          "score": 9,
          "max": 10
        },
        "combo_supportive_coverage": {
          "score": 10,
          "max": 10
        }
      },
      "report_path": "experiment_reports\\HN3-007_report.json",
      "status": "evaluated"
    },
    {
      "case_id": "HN3-008",
      "quality_score": 72,
      "dimensions": {
        "structural_integrity": {
          "score": 15,
          "max": 15
        },
        "evidence_depth": {
          "score": 14,
          "max": 25
        },
        "tier_coverage": {
          "score": 10,
          "max": 10
        },
        "rating_calibration": {
          "score": 0,
          "max": 15
        },
        "source_quality": {
          "score": 14,
          "max": 15
        },
        "clinical_relevance": {
          "score": 9,
          "max": 10
        },
        "combo_supportive_coverage": {
          "score": 10,
          "max": 10
        }
      },
      "report_path": "experiment_reports\\HN3-008_report.json",
      "status": "evaluated"
    },
    {
      "case_id": "HN3-009",
      "quality_score": 92,
      "dimensions": {
        "structural_integrity": {
          "score": 15,
          "max": 15
        },
        "evidence_depth": {
          "score": 21,
          "max": 25
        },
        "tier_coverage": {
          "score": 10,
          "max": 10
        },
        "rating_calibration": {
          "score": 12,
          "max": 15
        },
        "source_quality": {
          "score": 15,
          "max": 15
        },
        "clinical_relevance": {
          "score": 9,
          "max": 10
        },
        "combo_supportive_coverage": {
          "score": 10,
          "max": 10
        }
      },
      "report_path": "experiment_reports\\HN3-009_report.json",
      "status": "evaluated"
    },
    {
      "case_id": "HN3-010",
      "quality_score": 93,
      "dimensions": {
        "structural_integrity": {
          "score": 15,
          "max": 15
        },
        "evidence_depth": {
          "score": 21,
          "max": 25
        },
        "tier_coverage": {
          "score": 10,
          "max": 10
        },
        "rating_calibration": {
          "score": 13,
          "max": 15
        },
        "source_quality": {
          "score": 15,
          "max": 15
        },
        "clinical_relevance": {
          "score": 9,
          "max": 10
        },
        "combo_supportive_coverage": {
          "score": 10,
          "max": 10
        }
      },
      "report_path": "experiment_reports\\HN3-010_report.json",
      "status": "evaluated"
    },
    {
      "case_id": "HN3-011",
      "quality_score": 66,
      "dimensions": {
        "structural_integrity": {
          "score": 15,
          "max": 15
        },
        "evidence_depth": {
          "score": 10,
          "max": 25
        },
        "tier_coverage": {
          "score": 8,
          "max": 10
        },
        "rating_calibration": {
          "score": 0,
          "max": 15
        },
        "source_quality": {
          "score": 14,
          "max": 15
        },
        "clinical_relevance": {
          "score": 9,
          "max": 10
        },
        "combo_supportive_coverage": {
          "score": 10,
          "max": 10
        }
      },
      "report_path": "experiment_reports\\HN3-011_report.json",
      "status": "evaluated"
    },
    {
      "case_id": "HN3-012",
      "quality_score": 70,
      "dimensions": {
        "structural_integrity": {
          "score": 15,
          "max": 15
        },
        "evidence_depth": {
          "score": 12,
          "max": 25
        },
        "tier_coverage": {
          "score": 10,
          "max": 10
        },
        "rating_calibration": {
          "score": 0,
          "max": 15
        },
        "source_quality": {
          "score": 14,
          "max": 15
        },
        "clinical_relevance": {
          "score": 9,
          "max": 10
        },
        "combo_supportive_coverage": {
          "score": 10,
          "max": 10
        }
      },
      "report_path": "experiment_reports\\HN3-012_report.json",
      "status": "evaluated"
    },
    {
      "case_id": "HN3-013",
      "quality_score": 70,
      "dimensions": {
        "structural_integrity": {
          "score": 15,
          "max": 15
        },
        "evidence_depth": {
          "score": 14,
          "max": 25
        },
        "tier_coverage": {
          "score": 8,
          "max": 10
        },
        "rating_calibration": {
          "score": 0,
          "max": 15
        },
        "source_quality": {
          "score": 14,
          "max": 15
        },
        "clinical_relevance": {
          "score": 9,
          "max": 10
        },
        "combo_supportive_coverage": {
          "score": 10,
          "max": 10
        }
      },
      "report_path": "experiment_reports\\HN3-013_report.json",
      "status": "evaluated"
    },
    {
      "case_id": "HN3-014",
      "quality_score": 66,
      "dimensions": {
        "structural_integrity": {
          "score": 15,
          "max": 15
        },
        "evidence_depth": {
          "score": 9,
          "max": 25
        },
        "tier_coverage": {
          "score": 10,
          "max": 10
        },
        "rating_calibration": {
          "score": 0,
          "max": 15
        },
        "source_quality": {
          "score": 14,
          "max": 15
        },
        "clinical_relevance": {
          "score": 9,
          "max": 10
        },
        "combo_supportive_coverage": {
          "score": 9,
          "max": 10
        }
      },
      "report_path": "experiment_reports\\HN3-014_report.json",
      "status": "evaluated"
    },
    {
      "case_id": "HN3-015",
      "quality_score": 92,
      "dimensions": {
        "structural_integrity": {
          "score": 15,
          "max": 15
        },
        "evidence_depth": {
          "score": 22,
          "max": 25
        },
        "tier_coverage": {
          "score": 10,
          "max": 10
        },
        "rating_calibration": {
          "score": 11,
          "max": 15
        },
        "source_quality": {
          "score": 15,
          "max": 15
        },
        "clinical_relevance": {
          "score": 9,
          "max": 10
        },
        "combo_supportive_coverage": {
          "score": 10,
          "max": 10
        }
      },
      "report_path": "experiment_reports\\HN3-015_report.json",
      "status": "evaluated"
    },
    {
      "case_id": "HN3-016",
      "quality_score": 73,
      "dimensions": {
        "structural_integrity": {
          "score": 15,
          "max": 15
        },
        "evidence_depth": {
          "score": 14,
          "max": 25
        },
        "tier_coverage": {
          "score": 10,
          "max": 10
        },
        "rating_calibration": {
          "score": 0,
          "max": 15
        },
        "source_quality": {
          "score": 15,
          "max": 15
        },
        "clinical_relevance": {
          "score": 9,
          "max": 10
        },
        "combo_supportive_coverage": {
          "score": 10,
          "max": 10
        }
      },
      "report_path": "experiment_reports\\HN3-016_report.json",
      "status": "evaluated"
    },
    {
      "case_id": "HN3-017",
      "quality_score": 70,
      "dimensions": {
        "structural_integrity": {
          "score": 15,
          "max": 15
        },
        "evidence_depth": {
          "score": 12,
          "max": 25
        },
        "tier_coverage": {
          "score": 10,
          "max": 10
        },
        "rating_calibration": {
          "score": 0,
          "max": 15
        },
        "source_quality": {
          "score": 14,
          "max": 15
        },
        "clinical_relevance": {
          "score": 9,
          "max": 10
        },
        "combo_supportive_coverage": {
          "score": 10,
          "max": 10
        }
      },
      "report_path": "experiment_reports\\HN3-017_report.json",
      "status": "evaluated"
    },
    {
      "case_id": "HN3-018",
      "quality_score": 71,
      "dimensions": {
        "structural_integrity": {
          "score": 15,
          "max": 15
        },
        "evidence_depth": {
          "score": 13,
          "max": 25
        },
        "tier_coverage": {
          "score": 10,
          "max": 10
        },
        "rating_calibration": {
          "score": 0,
          "max": 15
        },
        "source_quality": {
          "score": 14,
          "max": 15
        },
        "clinical_relevance": {
          "score": 9,
          "max": 10
        },
        "combo_supportive_coverage": {
          "score": 10,
          "max": 10
        }
      },
      "report_path": "experiment_reports\\HN3-018_report.json",
      "status": "evaluated"
    },
    {
      "case_id": "HN3-019",
      "quality_score": 71,
      "dimensions": {
        "structural_integrity": {
          "score": 15,
          "max": 15
        },
        "evidence_depth": {
          "score": 13,
          "max": 25
        },
        "tier_coverage": {
          "score": 10,
          "max": 10
        },
        "rating_calibration": {
          "score": 0,
          "max": 15
        },
        "source_quality": {
          "score": 14,
          "max": 15
        },
        "clinical_relevance": {
          "score": 9,
          "max": 10
        },
        "combo_supportive_coverage": {
          "score": 10,
          "max": 10
        }
      },
      "report_path": "experiment_reports\\HN3-019_report.json",
      "status": "evaluated"
    },
    {
      "case_id": "HN3-020",
      "quality_score": 89,
      "dimensions": {
        "structural_integrity": {
          "score": 15,
          "max": 15
        },
        "evidence_depth": {
          "score": 17,
          "max": 25
        },
        "tier_coverage": {
          "score": 10,
          "max": 10
        },
        "rating_calibration": {
          "score": 13,
          "max": 15
        },
        "source_quality": {
          "score": 15,
          "max": 15
        },
        "clinical_relevance": {
          "score": 9,
          "max": 10
        },
        "combo_supportive_coverage": {
          "score": 10,
          "max": 10
        }
      },
      "report_path": "experiment_reports\\HN3-020_report.json",
      "status": "evaluated"
    },
    {
      "case_id": "HN3-021",
      "quality_score": 68,
      "dimensions": {
        "structural_integrity": {
          "score": 15,
          "max": 15
        },
        "evidence_depth": {
          "score": 10,
          "max": 25
        },
        "tier_coverage": {
          "score": 10,
          "max": 10
        },
        "rating_calibration": {
          "score": 0,
          "max": 15
        },
        "source_quality": {
          "score": 15,
          "max": 15
        },
        "clinical_relevance": {
          "score": 9,
          "max": 10
        },
        "combo_supportive_coverage": {
          "score": 9,
          "max": 10
        }
      },
      "report_path": "experiment_reports\\HN3-021_report.json",
      "status": "evaluated"
    },
    {
      "case_id": "HN3-022",
      "quality_score": 68,
      "dimensions": {
        "structural_integrity": {
          "score": 15,
          "max": 15
        },
        "evidence_depth": {
          "score": 12,
          "max": 25
        },
        "tier_coverage": {
          "score": 8,
          "max": 10
        },
        "rating_calibration": {
          "score": 0,
          "max": 15
        },
        "source_quality": {
          "score": 15,
          "max": 15
        },
        "clinical_relevance": {
          "score": 9,
          "max": 10
        },
        "combo_supportive_coverage": {
          "score": 9,
          "max": 10
        }
      },
      "report_path": "experiment_reports\\HN3-022_report.json",
      "status": "evaluated"
    },
    {
      "case_id": "HN3-023",
      "quality_score": 69,
      "dimensions": {
        "structural_integrity": {
          "score": 15,
          "max": 15
        },
        "evidence_depth": {
          "score": 10,
          "max": 25
        },
        "tier_coverage": {
          "score": 10,
          "max": 10
        },
        "rating_calibration": {
          "score": 0,
          "max": 15
        },
        "source_quality": {
          "score": 15,
          "max": 15
        },
        "clinical_relevance": {
          "score": 9,
          "max": 10
        },
        "combo_supportive_coverage": {
          "score": 10,
          "max": 10
        }
      },
      "report_path": "experiment_reports\\HN3-023_report.json",
      "status": "evaluated"
    },
    {
      "case_id": "HN3-024",
      "quality_score": 88,
      "dimensions": {
        "structural_integrity": {
          "score": 15,
          "max": 15
        },
        "evidence_depth": {
          "score": 18,
          "max": 25
        },
        "tier_coverage": {
          "score": 8,
          "max": 10
        },
        "rating_calibration": {
          "score": 13,
          "max": 15
        },
        "source_quality": {
          "score": 15,
          "max": 15
        },
        "clinical_relevance": {
          "score": 9,
          "max": 10
        },
        "combo_supportive_coverage": {
          "score": 10,
          "max": 10
        }
      },
      "report_path": "experiment_reports\\HN3-024_report.json",
      "status": "evaluated"
    },
    {
      "case_id": "HN3-025",
      "quality_score": 91,
      "dimensions": {
        "structural_integrity": {
          "score": 15,
          "max": 15
        },
        "evidence_depth": {
          "score": 18,
          "max": 25
        },
        "tier_coverage": {
          "score": 10,
          "max": 10
        },
        "rating_calibration": {
          "score": 14,
          "max": 15
        },
        "source_quality": {
          "score": 15,
          "max": 15
        },
        "clinical_relevance": {
          "score": 9,
          "max": 10
        },
        "combo_supportive_coverage": {
          "score": 10,
          "max": 10
        }
      },
      "report_path": "experiment_reports\\HN3-025_report.json",
      "status": "evaluated"
    },
    {
      "case_id": "HN3-026",
      "quality_score": 85,
      "dimensions": {
        "structural_integrity": {
          "score": 15,
          "max": 15
        },
        "evidence_depth": {
          "score": 12,
          "max": 25
        },
        "tier_coverage": {
          "score": 10,
          "max": 10
        },
        "rating_calibration": {
          "score": 14,
          "max": 15
        },
        "source_quality": {
          "score": 15,
          "max": 15
        },
        "clinical_relevance": {
          "score": 9,
          "max": 10
        },
        "combo_supportive_coverage": {
          "score": 10,
          "max": 10
        }
      },
      "report_path": "experiment_reports\\HN3-026_report.json",
      "status": "evaluated"
    },
    {
      "case_id": "HN3-027",
      "quality_score": 86,
      "dimensions": {
        "structural_integrity": {
          "score": 15,
          "max": 15
        },
        "evidence_depth": {
          "score": 13,
          "max": 25
        },
        "tier_coverage": {
          "score": 10,
          "max": 10
        },
        "rating_calibration": {
          "score": 14,
          "max": 15
        },
        "source_quality": {
          "score": 15,
          "max": 15
        },
        "clinical_relevance": {
          "score": 9,
          "max": 10
        },
        "combo_supportive_coverage": {
          "score": 10,
          "max": 10
        }
      },
      "report_path": "experiment_reports\\HN3-027_report.json",
      "status": "evaluated"
    },
    {
      "case_id": "HN3-028",
      "quality_score": 84,
      "dimensions": {
        "structural_integrity": {
          "score": 15,
          "max": 15
        },
        "evidence_depth": {
          "score": 12,
          "max": 25
        },
        "tier_coverage": {
          "score": 8,
          "max": 10
        },
        "rating_calibration": {
          "score": 15,
          "max": 15
        },
        "source_quality": {
          "score": 15,
          "max": 15
        },
        "clinical_relevance": {
          "score": 9,
          "max": 10
        },
        "combo_supportive_coverage": {
          "score": 10,
          "max": 10
        }
      },
      "report_path": "experiment_reports\\HN3-028_report.json",
      "status": "evaluated"
    },
    {
      "case_id": "HN3-029",
      "quality_score": 71,
      "dimensions": {
        "structural_integrity": {
          "score": 15,
          "max": 15
        },
        "evidence_depth": {
          "score": 12,
          "max": 25
        },
        "tier_coverage": {
          "score": 10,
          "max": 10
        },
        "rating_calibration": {
          "score": 0,
          "max": 15
        },
        "source_quality": {
          "score": 15,
          "max": 15
        },
        "clinical_relevance": {
          "score": 9,
          "max": 10
        },
        "combo_supportive_coverage": {
          "score": 10,
          "max": 10
        }
      },
      "report_path": "experiment_reports\\HN3-029_report.json",
      "status": "evaluated"
    },
    {
      "case_id": "HN3-030",
      "quality_score": 92,
      "dimensions": {
        "structural_integrity": {
          "score": 15,
          "max": 15
        },
        "evidence_depth": {
          "score": 21,
          "max": 25
        },
        "tier_coverage": {
          "score": 10,
          "max": 10
        },
        "rating_calibration": {
          "score": 12,
          "max": 15
        },
        "source_quality": {
          "score": 15,
          "max": 15
        },
        "clinical_relevance": {
          "score": 9,
          "max": 10
        },
        "combo_supportive_coverage": {
          "score": 10,
          "max": 10
        }
      },
      "report_path": "experiment_reports\\HN3-030_report.json",
      "status": "evaluated"
    },
    {
      "case_id": "HN3-031",
      "quality_score": 72,
      "dimensions": {
        "structural_integrity": {
          "score": 15,
          "max": 15
        },
        "evidence_depth": {
          "score": 15,
          "max": 25
        },
        "tier_coverage": {
          "score": 10,
          "max": 10
        },
        "rating_calibration": {
          "score": 0,
          "max": 15
        },
        "source_quality": {
          "score": 14,
          "max": 15
        },
        "clinical_relevance": {
          "score": 8,
          "max": 10
        },
        "combo_supportive_coverage": {
          "score": 10,
          "max": 10
        }
      },
      "report_path": "experiment_reports\\HN3-031_report.json",
      "status": "evaluated"
    },
    {
      "case_id": "HN3-032",
      "quality_score": 65,
      "dimensions": {
        "structural_integrity": {
          "score": 15,
          "max": 15
        },
        "evidence_depth": {
          "score": 11,
          "max": 25
        },
        "tier_coverage": {
          "score": 10,
          "max": 10
        },
        "rating_calibration": {
          "score": 0,
          "max": 15
        },
        "source_quality": {
          "score": 14,
          "max": 15
        },
        "clinical_relevance": {
          "score": 7,
          "max": 10
        },
        "combo_supportive_coverage": {
          "score": 8,
          "max": 10
        }
      },
      "report_path": "experiment_reports\\HN3-032_report.json",
      "status": "evaluated"
    },
    {
      "case_id": "HN3-033",
      "quality_score": 66,
      "dimensions": {
        "structural_integrity": {
          "score": 15,
          "max": 15
        },
        "evidence_depth": {
          "score": 11,
          "max": 25
        },
        "tier_coverage": {
          "score": 10,
          "max": 10
        },
        "rating_calibration": {
          "score": 0,
          "max": 15
        },
        "source_quality": {
          "score": 14,
          "max": 15
        },
        "clinical_relevance": {
          "score": 8,
          "max": 10
        },
        "combo_supportive_coverage": {
          "score": 8,
          "max": 10
        }
      },
      "report_path": "experiment_reports\\HN3-033_report.json",
      "status": "evaluated"
    },
    {
      "case_id": "HN3-034",
      "quality_score": 69,
      "dimensions": {
        "structural_integrity": {
          "score": 15,
          "max": 15
        },
        "evidence_depth": {
          "score": 12,
          "max": 25
        },
        "tier_coverage": {
          "score": 10,
          "max": 10
        },
        "rating_calibration": {
          "score": 0,
          "max": 15
        },
        "source_quality": {
          "score": 14,
          "max": 15
        },
        "clinical_relevance": {
          "score": 8,
          "max": 10
        },
        "combo_supportive_coverage": {
          "score": 10,
          "max": 10
        }
      },
      "report_path": "experiment_reports\\HN3-034_report.json",
      "status": "evaluated"
    },
    {
      "case_id": "HN3-035",
      "quality_score": 95,
      "dimensions": {
        "structural_integrity": {
          "score": 15,
          "max": 15
        },
        "evidence_depth": {
          "score": 23,
          "max": 25
        },
        "tier_coverage": {
          "score": 10,
          "max": 10
        },
        "rating_calibration": {
          "score": 13,
          "max": 15
        },
        "source_quality": {
          "score": 15,
          "max": 15
        },
        "clinical_relevance": {
          "score": 9,
          "max": 10
        },
        "combo_supportive_coverage": {
          "score": 10,
          "max": 10
        }
      },
      "report_path": "experiment_reports\\HN3-035_report.json",
      "status": "evaluated"
    },
    {
      "case_id": "HN3-036",
      "quality_score": 69,
      "dimensions": {
        "structural_integrity": {
          "score": 15,
          "max": 15
        },
        "evidence_depth": {
          "score": 11,
          "max": 25
        },
        "tier_coverage": {
          "score": 10,
          "max": 10
        },
        "rating_calibration": {
          "score": 0,
          "max": 15
        },
        "source_quality": {
          "score": 14,
          "max": 15
        },
        "clinical_relevance": {
          "score": 9,
          "max": 10
        },
        "combo_supportive_coverage": {
          "score": 10,
          "max": 10
        }
      },
      "report_path": "experiment_reports\\HN3-036_report.json",
      "status": "evaluated"
    },
    {
      "case_id": "HN3-037",
      "quality_score": 68,
      "dimensions": {
        "structural_integrity": {
          "score": 15,
          "max": 15
        },
        "evidence_depth": {
          "score": 11,
          "max": 25
        },
        "tier_coverage": {
          "score": 10,
          "max": 10
        },
        "rating_calibration": {
          "score": 0,
          "max": 15
        },
        "source_quality": {
          "score": 14,
          "max": 15
        },
        "clinical_relevance": {
          "score": 9,
          "max": 10
        },
        "combo_supportive_coverage": {
          "score": 9,
          "max": 10
        }
      },
      "report_path": "experiment_reports\\HN3-037_report.json",
      "status": "evaluated"
    },
    {
      "case_id": "HN3-038",
      "quality_score": 70,
      "dimensions": {
        "structural_integrity": {
          "score": 15,
          "max": 15
        },
        "evidence_depth": {
          "score": 12,
          "max": 25
        },
        "tier_coverage": {
          "score": 10,
          "max": 10
        },
        "rating_calibration": {
          "score": 0,
          "max": 15
        },
        "source_quality": {
          "score": 14,
          "max": 15
        },
        "clinical_relevance": {
          "score": 9,
          "max": 10
        },
        "combo_supportive_coverage": {
          "score": 10,
          "max": 10
        }
      },
      "report_path": "experiment_reports\\HN3-038_report.json",
      "status": "evaluated"
    },
    {
      "case_id": "HN3-039",
      "quality_score": 93,
      "dimensions": {
        "structural_integrity": {
          "score": 15,
          "max": 15
        },
        "evidence_depth": {
          "score": 21,
          "max": 25
        },
        "tier_coverage": {
          "score": 10,
          "max": 10
        },
        "rating_calibration": {
          "score": 13,
          "max": 15
        },
        "source_quality": {
          "score": 15,
          "max": 15
        },
        "clinical_relevance": {
          "score": 9,
          "max": 10
        },
        "combo_supportive_coverage": {
          "score": 10,
          "max": 10
        }
      },
      "report_path": "experiment_reports\\HN3-039_report.json",
      "status": "evaluated"
    },
    {
      "case_id": "HN3-040",
      "quality_score": 93,
      "dimensions": {
        "structural_integrity": {
          "score": 15,
          "max": 15
        },
        "evidence_depth": {
          "score": 22,
          "max": 25
        },
        "tier_coverage": {
          "score": 10,
          "max": 10
        },
        "rating_calibration": {
          "score": 12,
          "max": 15
        },
        "source_quality": {
          "score": 15,
          "max": 15
        },
        "clinical_relevance": {
          "score": 9,
          "max": 10
        },
        "combo_supportive_coverage": {
          "score": 10,
          "max": 10
        }
      },
      "report_path": "experiment_reports\\HN3-040_report.json",
      "status": "evaluated"
    },
    {
      "case_id": "HN3-041",
      "quality_score": 69,
      "dimensions": {
        "structural_integrity": {
          "score": 15,
          "max": 15
        },
        "evidence_depth": {
          "score": 11,
          "max": 25
        },
        "tier_coverage": {
          "score": 10,
          "max": 10
        },
        "rating_calibration": {
          "score": 0,
          "max": 15
        },
        "source_quality": {
          "score": 15,
          "max": 15
        },
        "clinical_relevance": {
          "score": 8,
          "max": 10
        },
        "combo_supportive_coverage": {
          "score": 10,
          "max": 10
        }
      },
      "report_path": "experiment_reports\\HN3-041_report.json",
      "status": "evaluated"
    },
    {
      "case_id": "HN3-042",
      "quality_score": 64,
      "dimensions": {
        "structural_integrity": {
          "score": 15,
          "max": 15
        },
        "evidence_depth": {
          "score": 10,
          "max": 25
        },
        "tier_coverage": {
          "score": 8,
          "max": 10
        },
        "rating_calibration": {
          "score": 0,
          "max": 15
        },
        "source_quality": {
          "score": 14,
          "max": 15
        },
        "clinical_relevance": {
          "score": 8,
          "max": 10
        },
        "combo_supportive_coverage": {
          "score": 9,
          "max": 10
        }
      },
      "report_path": "experiment_reports\\HN3-042_report.json",
      "status": "evaluated"
    },
    {
      "case_id": "HN3-043",
      "quality_score": 68,
      "dimensions": {
        "structural_integrity": {
          "score": 15,
          "max": 15
        },
        "evidence_depth": {
          "score": 10,
          "max": 25
        },
        "tier_coverage": {
          "score": 10,
          "max": 10
        },
        "rating_calibration": {
          "score": 0,
          "max": 15
        },
        "source_quality": {
          "score": 14,
          "max": 15
        },
        "clinical_relevance": {
          "score": 9,
          "max": 10
        },
        "combo_supportive_coverage": {
          "score": 10,
          "max": 10
        }
      },
      "report_path": "experiment_reports\\HN3-043_report.json",
      "status": "evaluated"
    },
    {
      "case_id": "HN3-044",
      "quality_score": 93,
      "dimensions": {
        "structural_integrity": {
          "score": 15,
          "max": 15
        },
        "evidence_depth": {
          "score": 21,
          "max": 25
        },
        "tier_coverage": {
          "score": 10,
          "max": 10
        },
        "rating_calibration": {
          "score": 13,
          "max": 15
        },
        "source_quality": {
          "score": 15,
          "max": 15
        },
        "clinical_relevance": {
          "score": 9,
          "max": 10
        },
        "combo_supportive_coverage": {
          "score": 10,
          "max": 10
        }
      },
      "report_path": "experiment_reports\\HN3-044_report.json",
      "status": "evaluated"
    },
    {
      "case_id": "HN3-045",
      "quality_score": 94,
      "dimensions": {
        "structural_integrity": {
          "score": 15,
          "max": 15
        },
        "evidence_depth": {
          "score": 23,
          "max": 25
        },
        "tier_coverage": {
          "score": 10,
          "max": 10
        },
        "rating_calibration": {
          "score": 12,
          "max": 15
        },
        "source_quality": {
          "score": 15,
          "max": 15
        },
        "clinical_relevance": {
          "score": 9,
          "max": 10
        },
        "combo_supportive_coverage": {
          "score": 10,
          "max": 10
        }
      },
      "report_path": "experiment_reports\\HN3-045_report.json",
      "status": "evaluated"
    },
    {
      "case_id": "HN3-046",
      "quality_score": 72,
      "dimensions": {
        "structural_integrity": {
          "score": 15,
          "max": 15
        },
        "evidence_depth": {
          "score": 13,
          "max": 25
        },
        "tier_coverage": {
          "score": 10,
          "max": 10
        },
        "rating_calibration": {
          "score": 0,
          "max": 15
        },
        "source_quality": {
          "score": 15,
          "max": 15
        },
        "clinical_relevance": {
          "score": 9,
          "max": 10
        },
        "combo_supportive_coverage": {
          "score": 10,
          "max": 10
        }
      },
      "report_path": "experiment_reports\\HN3-046_report.json",
      "status": "evaluated"
    },
    {
      "case_id": "HN3-047",
      "quality_score": 66,
      "dimensions": {
        "structural_integrity": {
          "score": 15,
          "max": 15
        },
        "evidence_depth": {
          "score": 9,
          "max": 25
        },
        "tier_coverage": {
          "score": 10,
          "max": 10
        },
        "rating_calibration": {
          "score": 0,
          "max": 15
        },
        "source_quality": {
          "score": 14,
          "max": 15
        },
        "clinical_relevance": {
          "score": 9,
          "max": 10
        },
        "combo_supportive_coverage": {
          "score": 9,
          "max": 10
        }
      },
      "report_path": "experiment_reports\\HN3-047_report.json",
      "status": "evaluated"
    },
    {
      "case_id": "HN3-048",
      "quality_score": 67,
      "dimensions": {
        "structural_integrity": {
          "score": 15,
          "max": 15
        },
        "evidence_depth": {
          "score": 9,
          "max": 25
        },
        "tier_coverage": {
          "score": 10,
          "max": 10
        },
        "rating_calibration": {
          "score": 0,
          "max": 15
        },
        "source_quality": {
          "score": 14,
          "max": 15
        },
        "clinical_relevance": {
          "score": 9,
          "max": 10
        },
        "combo_supportive_coverage": {
          "score": 10,
          "max": 10
        }
      },
      "report_path": "experiment_reports\\HN3-048_report.json",
      "status": "evaluated"
    },
    {
      "case_id": "HN3-049",
      "quality_score": 94,
      "dimensions": {
        "structural_integrity": {
          "score": 15,
          "max": 15
        },
        "evidence_depth": {
          "score": 22,
          "max": 25
        },
        "tier_coverage": {
          "score": 10,
          "max": 10
        },
        "rating_calibration": {
          "score": 13,
          "max": 15
        },
        "source_quality": {
          "score": 15,
          "max": 15
        },
        "clinical_relevance": {
          "score": 9,
          "max": 10
        },
        "combo_supportive_coverage": {
          "score": 10,
          "max": 10
        }
      },
      "report_path": "experiment_reports\\HN3-049_report.json",
      "status": "evaluated"
    },
    {
      "case_id": "HN3-050",
      "quality_score": 92,
      "dimensions": {
        "structural_integrity": {
          "score": 15,
          "max": 15
        },
        "evidence_depth": {
          "score": 21,
          "max": 25
        },
        "tier_coverage": {
          "score": 10,
          "max": 10
        },
        "rating_calibration": {
          "score": 12,
          "max": 15
        },
        "source_quality": {
          "score": 15,
          "max": 15
        },
        "clinical_relevance": {
          "score": 9,
          "max": 10
        },
        "combo_supportive_coverage": {
          "score": 10,
          "max": 10
        }
      },
      "report_path": "experiment_reports\\HN3-050_report.json",
      "status": "evaluated"
    },
    {
      "case_id": "HN3-051",
      "quality_score": 72,
      "dimensions": {
        "structural_integrity": {
          "score": 15,
          "max": 15
        },
        "evidence_depth": {
          "score": 16,
          "max": 25
        },
        "tier_coverage": {
          "score": 10,
          "max": 10
        },
        "rating_calibration": {
          "score": 0,
          "max": 15
        },
        "source_quality": {
          "score": 14,
          "max": 15
        },
        "clinical_relevance": {
          "score": 7,
          "max": 10
        },
        "combo_supportive_coverage": {
          "score": 10,
          "max": 10
        }
      },
      "report_path": "experiment_reports\\HN3-051_report.json",
      "status": "evaluated"
    },
    {
      "case_id": "HN3-052",
      "quality_score": 70,
      "dimensions": {
        "structural_integrity": {
          "score": 15,
          "max": 15
        },
        "evidence_depth": {
          "score": 12,
          "max": 25
        },
        "tier_coverage": {
          "score": 10,
          "max": 10
        },
        "rating_calibration": {
          "score": 0,
          "max": 15
        },
        "source_quality": {
          "score": 14,
          "max": 15
        },
        "clinical_relevance": {
          "score": 9,
          "max": 10
        },
        "combo_supportive_coverage": {
          "score": 10,
          "max": 10
        }
      },
      "report_path": "experiment_reports\\HN3-052_report.json",
      "status": "evaluated"
    },
    {
      "case_id": "HN3-053",
      "quality_score": 73,
      "dimensions": {
        "structural_integrity": {
          "score": 15,
          "max": 15
        },
        "evidence_depth": {
          "score": 16,
          "max": 25
        },
        "tier_coverage": {
          "score": 10,
          "max": 10
        },
        "rating_calibration": {
          "score": 0,
          "max": 15
        },
        "source_quality": {
          "score": 14,
          "max": 15
        },
        "clinical_relevance": {
          "score": 9,
          "max": 10
        },
        "combo_supportive_coverage": {
          "score": 9,
          "max": 10
        }
      },
      "report_path": "experiment_reports\\HN3-053_report.json",
      "status": "evaluated"
    },
    {
      "case_id": "HN3-054",
      "quality_score": 90,
      "dimensions": {
        "structural_integrity": {
          "score": 15,
          "max": 15
        },
        "evidence_depth": {
          "score": 22,
          "max": 25
        },
        "tier_coverage": {
          "score": 8,
          "max": 10
        },
        "rating_calibration": {
          "score": 11,
          "max": 15
        },
        "source_quality": {
          "score": 15,
          "max": 15
        },
        "clinical_relevance": {
          "score": 9,
          "max": 10
        },
        "combo_supportive_coverage": {
          "score": 10,
          "max": 10
        }
      },
      "report_path": "experiment_reports\\HN3-054_report.json",
      "status": "evaluated"
    },
    {
      "case_id": "HN3-055",
      "quality_score": 94,
      "dimensions": {
        "structural_integrity": {
          "score": 15,
          "max": 15
        },
        "evidence_depth": {
          "score": 22,
          "max": 25
        },
        "tier_coverage": {
          "score": 10,
          "max": 10
        },
        "rating_calibration": {
          "score": 13,
          "max": 15
        },
        "source_quality": {
          "score": 15,
          "max": 15
        },
        "clinical_relevance": {
          "score": 9,
          "max": 10
        },
        "combo_supportive_coverage": {
          "score": 10,
          "max": 10
        }
      },
      "report_path": "experiment_reports\\HN3-055_report.json",
      "status": "evaluated"
    },
    {
      "case_id": "HN3-056",
      "quality_score": 73,
      "dimensions": {
        "structural_integrity": {
          "score": 15,
          "max": 15
        },
        "evidence_depth": {
          "score": 15,
          "max": 25
        },
        "tier_coverage": {
          "score": 10,
          "max": 10
        },
        "rating_calibration": {
          "score": 0,
          "max": 15
        },
        "source_quality": {
          "score": 14,
          "max": 15
        },
        "clinical_relevance": {
          "score": 9,
          "max": 10
        },
        "combo_supportive_coverage": {
          "score": 10,
          "max": 10
        }
      },
      "report_path": "experiment_reports\\HN3-056_report.json",
      "status": "evaluated"
    },
    {
      "case_id": "HN3-057",
      "quality_score": 72,
      "dimensions": {
        "structural_integrity": {
          "score": 15,
          "max": 15
        },
        "evidence_depth": {
          "score": 14,
          "max": 25
        },
        "tier_coverage": {
          "score": 10,
          "max": 10
        },
        "rating_calibration": {
          "score": 0,
          "max": 15
        },
        "source_quality": {
          "score": 14,
          "max": 15
        },
        "clinical_relevance": {
          "score": 9,
          "max": 10
        },
        "combo_supportive_coverage": {
          "score": 10,
          "max": 10
        }
      },
      "report_path": "experiment_reports\\HN3-057_report.json",
      "status": "evaluated"
    },
    {
      "case_id": "HN3-058",
      "quality_score": 71,
      "dimensions": {
        "structural_integrity": {
          "score": 15,
          "max": 15
        },
        "evidence_depth": {
          "score": 13,
          "max": 25
        },
        "tier_coverage": {
          "score": 10,
          "max": 10
        },
        "rating_calibration": {
          "score": 0,
          "max": 15
        },
        "source_quality": {
          "score": 14,
          "max": 15
        },
        "clinical_relevance": {
          "score": 9,
          "max": 10
        },
        "combo_supportive_coverage": {
          "score": 10,
          "max": 10
        }
      },
      "report_path": "experiment_reports\\HN3-058_report.json",
      "status": "evaluated"
    },
    {
      "case_id": "HN3-059",
      "quality_score": 92,
      "dimensions": {
        "structural_integrity": {
          "score": 15,
          "max": 15
        },
        "evidence_depth": {
          "score": 22,
          "max": 25
        },
        "tier_coverage": {
          "score": 10,
          "max": 10
        },
        "rating_calibration": {
          "score": 12,
          "max": 15
        },
        "source_quality": {
          "score": 14,
          "max": 15
        },
        "clinical_relevance": {
          "score": 9,
          "max": 10
        },
        "combo_supportive_coverage": {
          "score": 10,
          "max": 10
        }
      },
      "report_path": "experiment_reports\\HN3-059_report.json",
      "status": "evaluated"
    },
    {
      "case_id": "HN3-060",
      "quality_score": 96,
      "dimensions": {
        "structural_integrity": {
          "score": 15,
          "max": 15
        },
        "evidence_depth": {
          "score": 23,
          "max": 25
        },
        "tier_coverage": {
          "score": 10,
          "max": 10
        },
        "rating_calibration": {
          "score": 14,
          "max": 15
        },
        "source_quality": {
          "score": 15,
          "max": 15
        },
        "clinical_relevance": {
          "score": 9,
          "max": 10
        },
        "combo_supportive_coverage": {
          "score": 10,
          "max": 10
        }
      },
      "report_path": "experiment_reports\\HN3-060_report.json",
      "status": "evaluated"
    }
  ]
}